pipinfo/__init__.py
pipinfo/library.py
pipinfo/main.py
pnu_pipinfo-0.9.4.data/data/man/man1/pipinfo.1.gz
pnu_pipinfo-0.9.4.dist-info/License
pnu_pipinfo-0.9.4.dist-info/METADATA
pnu_pipinfo-0.9.4.dist-info/WHEEL
pnu_pipinfo-0.9.4.dist-info/entry_points.txt
pnu_pipinfo-0.9.4.dist-info/top_level.txt
pnu_pipinfo-0.9.4.dist-info/RECORD
